hyper_sdk/__init__.py
hyper_sdk/akamai_input.py
hyper_sdk/datadome_input.py
hyper_sdk/incapsula_input.py
hyper_sdk/kasada_input.py
hyper_sdk/session.py
hyper_sdk/session_async.py
hyper_sdk/shared.py
hyper_sdk/trustdecision_input.py
hyper_sdk/akamai/__init__.py
hyper_sdk/akamai/pixel.py
hyper_sdk/akamai/script_path.py
hyper_sdk/akamai/sec_cpt.py
hyper_sdk/akamai/stop_signal.py
hyper_sdk/datadome/__init__.py
hyper_sdk/datadome/parse.py
hyper_sdk/incapsula/__init__.py
hyper_sdk/incapsula/dynamic.py
hyper_sdk/incapsula/utmvc.py
hyper_sdk/kasada/__init__.py
hyper_sdk/kasada/parse.py
hyper_sdk-2.12.1.dist-info/licenses/LICENSE
hyper_sdk-2.12.1.dist-info/METADATA
hyper_sdk-2.12.1.dist-info/WHEEL
hyper_sdk-2.12.1.dist-info/top_level.txt
hyper_sdk-2.12.1.dist-info/RECORD
