Metadata-Version: 2.4
Name: hyper_sdk
Version: 2.12.1
Summary: Hyper Solutions Python SDK
License: MIT License
Project-URL: homepage, https://github.com/Hyper-Solutions/hyper-sdk-py
Classifier: Intended Audience :: Developers
Classifier: License :: OSI Approved :: MIT License
Classifier: Programming Language :: Python :: 3
Classifier: Framework :: AsyncIO
Requires-Python: >=3.7
License-File: LICENSE
Requires-Dist: httpx[http2]>=0.24.0
Requires-Dist: certifi>=2024.2.2
Requires-Dist: charset-normalizer>=3.3.2
Requires-Dist: idna>=3.6
Requires-Dist: jsonpickle>=3.0.3
Requires-Dist: PyJWT>=2.8.0
Requires-Dist: urllib3>=2.2.1
Dynamic: license-file
